fcache/__init__.py
fcache/cache.py
fcache/posixemulation.py
fcache-0.4.7.dist-info/DESCRIPTION.rst
fcache-0.4.7.dist-info/METADATA
fcache-0.4.7.dist-info/metadata.json
fcache-0.4.7.dist-info/RECORD
fcache-0.4.7.dist-info/top_level.txt
fcache-0.4.7.dist-info/WHEEL
tests/__init__.py
tests/test_cache.py
