Metadata-Version: 1.1
Name: fcache
Version: 0.4.7
Summary: a dictionary-like, file-based cache module for Python
Home-page: https://github.com/tsroten/fcache
Author: Thomas Roten
Author-email: thomas@roten.us
License: UNKNOWN
Keywords: cache,file,serialize
Platform: any
Classifier: Programming Language :: Python
Classifier: Topic :: Software Development :: Libraries :: Python Modules
Classifier: Topic :: System :: Filesystems
Classifier: License :: OSI Approved :: MIT License
Classifier: Operating System :: OS Independent
Classifier: Intended Audience :: Developers
Classifier: Programming Language :: Python :: 2.7
Classifier: Programming Language :: Python :: 3
Classifier: Programming Language :: Python :: 3.4
Classifier: Programming Language :: Python :: 3.5
Classifier: Programming Language :: Python :: 3.6
